setup.py
hanoi/__init__.py
hanoi/api.py
hanoi/backend.py
hanoi.egg-info/PKG-INFO
hanoi.egg-info/SOURCES.txt
hanoi.egg-info/dependency_links.txt
hanoi.egg-info/not-zip-safe
hanoi.egg-info/requires.txt
hanoi.egg-info/top_level.txt
tests/__init__.py
tests/api.py
tests/backend.py