Metadata-Version: 1.0
Name: hanoi
Version: 0.0.2
Summary: Toggle on/off features. Rollout python port
Home-page: https://github.com/juandebravo/hanoi
Author: Juan de Bravo
Author-email: juandebravo@gmail.com
License: UNKNOWN
Platform: UNKNOWN
